bifabrik/__init__.py
bifabrik/base/Pipeline.py
bifabrik/base/Task.py
bifabrik/cfg/CompleteConfiguration.py
bifabrik/cfg/Configuration.py
bifabrik/cfg/CsvSourceConfiguration.py
bifabrik/cfg/DataDestinationConfigurationBase.py
bifabrik/cfg/DataSourceConfigurationBase.py
bifabrik/cfg/ExcelSourceConfiguration.py
bifabrik/cfg/JdbcSourceConfiguration.py
bifabrik/cfg/JsonSourceConfiguration.py
bifabrik/cfg/LineageConfigurationContainer.py
bifabrik/cfg/SharePointListSourceConfiguration.py
bifabrik/cfg/TableDestinationConfiguration.py
bifabrik/cfg/ValidationTransformationConfiguration.py
bifabrik/cfg/__init__.py
bifabrik/cfg/engine/ConfigContainer.py
bifabrik/cfg/engine/Configuration.py
bifabrik/cfg/specific/CsvConfiguration.py
bifabrik/cfg/specific/DestinationStorageConfiguration.py
bifabrik/cfg/specific/ExcelConfiguration.py
bifabrik/cfg/specific/FileSourceConfiguration.py
bifabrik/cfg/specific/JdbcConfiguration.py
bifabrik/cfg/specific/JsonConfiguration.py
bifabrik/cfg/specific/LineageConfiguration.py
bifabrik/cfg/specific/LogConfiguration.py
bifabrik/cfg/specific/MetadataStorageConfiguration.py
bifabrik/cfg/specific/SecurityConfiguration.py
bifabrik/cfg/specific/SourceStorageConfiguration.py
bifabrik/cfg/specific/TableConfiguration.py
bifabrik/cfg/specific/ValidationConfiguration.py
bifabrik/dst/CommonDestinationUtils.py
bifabrik/dst/DataDestination.py
bifabrik/dst/LakehouseTableDestination.py
bifabrik/dst/PandasDfDestination.py
bifabrik/dst/SparkDfDestination.py
bifabrik/dst/WarehouseTableDestination.py
bifabrik/dst/__init__.py
bifabrik/src/CsvSource.py
bifabrik/src/DataSource.py
bifabrik/src/ExcelSource.py
bifabrik/src/JdbcSource.py
bifabrik/src/JsonSource.py
bifabrik/src/PandasDfSource.py
bifabrik/src/SharePointListSource.py
bifabrik/src/SparkDfSource.py
bifabrik/src/SparkSqlSource.py
bifabrik/src/WarehouseSqlSource.py
bifabrik/src/__init__.py
bifabrik/tsf/DataTransformation.py
bifabrik/tsf/PandasDfTransformation.py
bifabrik/tsf/SparkDfTransformation.py
bifabrik-0.15.2.dist-info/METADATA
bifabrik-0.15.2.dist-info/WHEEL
bifabrik-0.15.2.dist-info/licenses/LICENSE
bifabrik-0.15.2.dist-info/RECORD
