Metadata-Version: 2.4
Name: bifabrik
Version: 0.15.2
Summary: Microsoft Fabric ETL toolbox
License-Expression: MIT
License-File: LICENSE
Author: Radovan Jankovič
Author-email: jankovic.rj@gmail.com
Requires-Python: >=3.10,<4.0
Classifier: Programming Language :: Python :: 3
Classifier: Programming Language :: Python :: 3.10
Classifier: Programming Language :: Python :: 3.11
Classifier: Programming Language :: Python :: 3.12
Classifier: Programming Language :: Python :: 3.13
Classifier: Programming Language :: Python :: 3.14
Requires-Dist: SharePlum (>=0.5.1)
Requires-Dist: glob2 (>=0.7)
Requires-Dist: pandas (>=2.0)
Requires-Dist: semantic-link (>=0.7.7)
Project-URL: Changelog, https://github.com/rjankovic/bifabrik/blob/main/CHANGELOG.md
Project-URL: Documentation, https://rjankovic.github.io/bifabrik/
Project-URL: Homepage, https://rjankovic.github.io/bifabrik/
Project-URL: Issues, https://github.com/rjankovic/bifabrik/issues
Project-URL: Repository, https://github.com/rjankovic/bifabrik/
